easycore/__init__.py
easycore/abstractions/__init__.py
easycore/abstractions/singleton_class.py
easycore/connectors/__init__.py
easycore/connectors/api_connector.py
easycore/ecelery/__init__.py
easycore/ecelery/custom_task.py
easycore/ecelery/shortcuts.py
easycore/econnections/__init__.py
easycore/econnections/mongodb.py
easycore/econnections/redis.py
easycore/efastapi/__init__.py
easycore/efastapi/api_app.py
easycore/efastapi/api_server.py
easycore/efaststream/__init__.py
easycore/efaststream/correlation_middleware.py
easycore/ehttpx/__init__.py
easycore/ehttpx/log_patcher.py
easycore/elogger/__init__.py
easycore/elogger/context.py
easycore/elogger/fastapi_middleware.py
easycore/elogger/function_timing.py
easycore/elogger/installer.py
easycore/elogger/log_filter.py
easycore/elogger/utils.py
easycore/env_settings/__init__.py
easycore/env_settings/base.py
easycore/env_settings/gunicorn_settings.py
easycore/env_settings/mongo_settings.py
easycore/env_settings/open_telemetry.py
easycore/env_settings/rabbitmq_settings.py
easycore/env_settings/redis_settings.py
easycore/env_settings/uvicorn_settings.py
easycore/etaskiq/__init__.py
easycore/etaskiq/custom_schedule.py
easycore/etaskiq/installler.py
easycore/etaskiq/middleware_correlation_id.py
easycore/etaskiq/middleware_logging.py
easycore/etaskiq/mongo_result_backend.py
easycore/etaskiq/mongo_schedule_source.py
easycore/etaskiq/serializer.py
easycore/open_telemetry/__init__.py
easycore/open_telemetry/installer.py
easycore/utils/__init__.py
pyeasycore-0.4.2.dist-info/METADATA
pyeasycore-0.4.2.dist-info/WHEEL
pyeasycore-0.4.2.dist-info/RECORD
